vectorizers/__init__.py
vectorizers/_vectorizers.py
vectorizers/_version.py
vectorizers/_window_kernels.py
vectorizers/base_cooccurrence_vectorizer.py
vectorizers/coo_utils.py
vectorizers/distances.py
vectorizers/distribution_vectorizer.py
vectorizers/edge_list_vectorizer.py
vectorizers/kde_vectorizer.py
vectorizers/linear_optimal_transport.py
vectorizers/mixed_gram_vectorizer.py
vectorizers/multi_token_cooccurence_vectorizer.py
vectorizers/ngram_token_cooccurence_vectorizer.py
vectorizers/ngram_vectorizer.py
vectorizers/preprocessing.py
vectorizers/signature_vectorizer.py
vectorizers/skip_gram_vectorizer.py
vectorizers/timed_token_cooccurrence_vectorizer.py
vectorizers/token_cooccurrence_vectorizer.py
vectorizers/tree_token_cooccurrence.py
vectorizers/utils.py
vectorizers/tests/__init__.py
vectorizers/tests/test_bpe.py
vectorizers/tests/test_common.py
vectorizers/tests/test_distances.py
vectorizers/tests/test_edge_list_vectorizer.py
vectorizers/tests/test_signature_vectorizer.py
vectorizers/tests/test_template.py
vectorizers/tests/test_transformers.py
vectorizers/transformers/__init__.py
vectorizers/transformers/categorical_columns.py
vectorizers/transformers/count_feature_compression.py
vectorizers/transformers/info_weight.py
vectorizers/transformers/row_desnoise.py
vectorizers/transformers/sliding_windows.py
vectorizers-0.2.2.dist-info/LICENSE
vectorizers-0.2.2.dist-info/METADATA
vectorizers-0.2.2.dist-info/WHEEL
vectorizers-0.2.2.dist-info/top_level.txt
vectorizers-0.2.2.dist-info/RECORD
